{
	"configurations" : 
	[
		{
			"directories" : 
			[
				{
					"build" : ".",
					"jsonFile" : "directory-.-Debug-f5ebdc15457944623624.json",
					"minimumCMakeVersion" : 
					{
						"string" : "3.22"
					},
					"projectIndex" : 0,
					"source" : ".",
					"targetIndexes" : 
					[
						0
					]
				}
			],
			"name" : "Debug",
			"projects" : 
			[
				{
					"directoryIndexes" : 
					[
						0
					],
					"name" : "2644",
					"targetIndexes" : 
					[
						0
					]
				}
			],
			"targets" : 
			[
				{
					"directoryIndex" : 0,
					"id" : "2644::@6890427a1f51a3e7e1df",
					"jsonFile" : "target-2644-Debug-55b663b6db1df51e665d.json",
					"name" : "2644",
					"projectIndex" : 0
				}
			]
		}
	],
	"kind" : "codemodel",
	"paths" : 
	{
		"build" : "/Users/ordo/Desktop/cs/boj/C++/2644/cmake-build-debug",
		"source" : "/Users/ordo/Desktop/cs/boj/C++/2644"
	},
	"version" : 
	{
		"major" : 2,
		"minor" : 3
	}
}
